setup.py
RHTool/RH.py
RHTool/__init__.py
RHTool.egg-info/PKG-INFO
RHTool.egg-info/SOURCES.txt
RHTool.egg-info/dependency_links.txt
RHTool.egg-info/top_level.txt