Metadata-Version: 1.0
Name: RHTool
Version: 0.1.2
Summary: RH packet
Home-page: https://github.com/fengmm521/pipProject
Author: mage
Author-email: mage@woodcol.com
License: MIT Licence
Keywords: pip,RHTool,rhtool,RH
Platform: any
